spider_feeder/__init__.py
spider_feeder/loaders.py
spider_feeder/file_handler/__init__.py
spider_feeder/file_handler/local.py
spider_feeder/file_handler/s3.py
spider_feeder/store/__init__.py
spider_feeder/store/base_store.py
spider_feeder/store/file_store.py
spider_feeder/store/parser.py
spider_feeder/store/scrapinghub_collection.py
spider_feeder/store/file_handler/__init__.py
spider_feeder/store/file_handler/local.py
spider_feeder/store/file_handler/s3.py
tests/__init__.py
tests/test_loaders.py
spider_feeder-0.2.0.dist-info/LICENSE.txt
spider_feeder-0.2.0.dist-info/METADATA
spider_feeder-0.2.0.dist-info/WHEEL
spider_feeder-0.2.0.dist-info/top_level.txt
spider_feeder-0.2.0.dist-info/RECORD
