Metadata-Version: 2.1
Name: spider-feeder
Version: 0.2.0
Summary: spider-feeder is a library to help loading inputs to scrapy spiders.
Home-page: https://github.com/ejulio/spider-feeder
Author: Júlio César Batista
Author-email: julio.batista@outlook.com
License: MIT
Platform: UNKNOWN
Classifier: Development Status :: 3 - Alpha
Classifier: Framework :: Scrapy
Classifier: Intended Audience :: Developers
Classifier: License :: OSI Approved :: MIT License
Classifier: Operating System :: OS Independent
Classifier: Programming Language :: Python
Classifier: Programming Language :: Python :: 3
Classifier: Programming Language :: Python :: 3.4
Classifier: Programming Language :: Python :: 3.5
Classifier: Programming Language :: Python :: 3.6
Classifier: Programming Language :: Python :: 3.7
Requires-Dist: scrapy
Provides-Extra: collections
Requires-Dist: python-scrapinghub ; extra == 'collections'
Provides-Extra: pep8
Requires-Dist: flake8 ; extra == 'pep8'
Provides-Extra: s3
Requires-Dist: botocore ; extra == 's3'
